recreate_sdk/__init__.py
recreate_sdk/_base_client.py
recreate_sdk/_client.py
recreate_sdk/_compat.py
recreate_sdk/_constants.py
recreate_sdk/_exceptions.py
recreate_sdk/_files.py
recreate_sdk/_models.py
recreate_sdk/_qs.py
recreate_sdk/_resource.py
recreate_sdk/_response.py
recreate_sdk/_streaming.py
recreate_sdk/_types.py
recreate_sdk/_version.py
recreate_sdk/py.typed
recreate_sdk/_utils/__init__.py
recreate_sdk/_utils/_compat.py
recreate_sdk/_utils/_datetime_parse.py
recreate_sdk/_utils/_logs.py
recreate_sdk/_utils/_proxy.py
recreate_sdk/_utils/_reflection.py
recreate_sdk/_utils/_resources_proxy.py
recreate_sdk/_utils/_streams.py
recreate_sdk/_utils/_sync.py
recreate_sdk/_utils/_transform.py
recreate_sdk/_utils/_typing.py
recreate_sdk/_utils/_utils.py
recreate_sdk/lib/.keep
recreate_sdk/resources/__init__.py
recreate_sdk/resources/enterprise_api/__init__.py
recreate_sdk/resources/enterprise_api/enterprise_api.py
recreate_sdk/resources/enterprise_api/recreate.py
recreate_sdk/types/__init__.py
recreate_sdk/types/enterprise_api_unprotect_pdf_params.py
recreate_sdk/types/enterprise_api_validate_token_params.py
recreate_sdk/types/enterprise_api_validate_token_response.py
recreate_sdk/types/enterprise_api/__init__.py
recreate_sdk/types/enterprise_api/enterprise_api_response.py
recreate_sdk/types/enterprise_api/recreate_create_params.py
recreate_sdk/types/enterprise_api/recreate_get_json_response.py
recreate_sdk/types/enterprise_api/recreate_retrieve_status_params.py
recreate_sdk-1.2.7.dist-info/METADATA
recreate_sdk-1.2.7.dist-info/WHEEL
recreate_sdk-1.2.7.dist-info/licenses/LICENSE
recreate_sdk-1.2.7.dist-info/RECORD
